reCBZ/__init__.py
reCBZ/__main__.py
reCBZ/archive.py
reCBZ/config.py
reCBZ/defaults.toml
reCBZ/epub.py
reCBZ/formats.py
reCBZ/profiles.py
reCBZ/util.py
reCBZ/wrappers.py
reCBZ2-0.8.0.dist-info/LICENSE
reCBZ2-0.8.0.dist-info/METADATA
reCBZ2-0.8.0.dist-info/WHEEL
reCBZ2-0.8.0.dist-info/entry_points.txt
reCBZ2-0.8.0.dist-info/top_level.txt
reCBZ2-0.8.0.dist-info/RECORD
