Metadata-Version: 2.1
Name: reCBZ2
Version: 0.8.0
Summary: Utility for repacking and optmizing manga & comic book archives
License: GPLv3
Project-URL: Homepage, https://github.com/avalonv/reCBZ
Keywords: manga,comics,cbz,ebook,epub
Classifier: License :: OSI Approved :: GNU General Public License v3 (GPLv3)
Classifier: Programming Language :: Python
Classifier: Programming Language :: Python :: 3
Classifier: Topic :: Scientific/Engineering :: Image Processing
Classifier: Topic :: System :: Archiving
Classifier: Topic :: System :: Archiving :: Compression
Classifier: Topic :: Utilities
Requires-Python: >=3.9
License-File: LICENSE
Requires-Dist: pillow >=9.1
Requires-Dist: ebooklib >=0.18
Provides-Extra: dev
Requires-Dist: bumpver ; extra == 'dev'
Requires-Dist: pip-tools ; extra == 'dev'
